gittrail/__init__.py
gittrail/core.py
gittrail/exceptions.py
gittrail/test_core.py
gittrail/test_helpers.py
gittrail/test_utils.py
gittrail/utils.py
gittrail-0.1.1.dist-info/LICENSE
gittrail-0.1.1.dist-info/METADATA
gittrail-0.1.1.dist-info/WHEEL
gittrail-0.1.1.dist-info/top_level.txt
gittrail-0.1.1.dist-info/RECORD
