Metadata-Version: 2.1
Name: gittrail
Version: 0.1.1
Summary: Context manager for enforcing links between data pipeline outputs and git history.
Home-page: https://github.com/michaelosthege/gittrail
Author: Michael Osthege
Author-email: michael.osthege@outlook.com
License: AGPLv3
Platform: UNKNOWN
Classifier: Programming Language :: Python
Classifier: Operating System :: OS Independent
Classifier: License :: OSI Approved :: GNU Affero General Public License v3
Classifier: Intended Audience :: Science/Research
Requires-Python: >=3.6
License-File: LICENSE
Requires-Dist: filelock
